Metadata-Version: 2.1
Name: pygpiotools
Version: 0.1.33
Summary: Python tools & API to control GPIO pins of common USB_to_UART converters
Home-page: http://github.com/RC-MODULE/rumboot-tools
Author: Andrew Andrianov
Author-email: andrew@ncrmnt.org
License: GPL
Platform: any
